tencentcos_storage/__init__.py
tencentcos_storage/file.py
tencentcos_storage/storage.py
django_tencentcos_storage-0.2.1.dist-info/LICENSE
django_tencentcos_storage-0.2.1.dist-info/METADATA
django_tencentcos_storage-0.2.1.dist-info/WHEEL
django_tencentcos_storage-0.2.1.dist-info/RECORD
